Workbook

Sheet Sheet1
Z1: Male Vs Female | AE1: Average Age
E2: Gender | F2: Age | G2: Column1 | H2: Field of Work | I2: Column2 | J2: Level of Education | K2: No. of Children | L2: No. of Vehicles | M2: Income | N2: Column3 | O2: Area | P2: Value of The House | Q2: Mortage left | R2: Car Value | S2: Car Debit Left | T2: Debts | U2: Investments | V2: Net Worth | W2: Total Value of Debts | Z2: Male | AA2: Female | AB2: Number of Male | AC2: Number of Female | AE2: =AVERAGE(Table1[Age]) -> 34.732932 | AG2: Teaching | AH2: Health | AJ2: Field of Work | AL2: Level of Education | AQ2: Agriculture | AR2: IT | AS2: Construction | AT2: General Work | AV2: AVERAGE INCOME | AX2: A Value of Car | AY2: Average value of one car | AZ2: Debt greater than $20,000 | BB2: Number of peaople with debt greater than x | BC2: Percentage left to pay | BD2: Less than 30% | BE2: =Dashboard!Z14 -> 0.2 | BF2: No. of People that has X% left in their mortgage | BG2: Average Income per Territory | BJ2: Average Income per Sector | BM2: the percentage of people with debts higher than their yearly income | BO2: Average age of people with a netwoth higher than their yealy income 50000
D3: =RANDBETWEEN(1,2) -> 1 | E3: =IF(D3=1,"Male","Female") -> Male | F3: =RANDBETWEEN(25,45) -> 30 | G3: =RANDBETWEEN(1,6) -> 4 | H3: =VLOOKUP(G3,$AI$3:$AJ$8,2) -> IT | I3: =RANDBETWEEN(1,5) -> 5 | J3: =+VLOOKUP(I3,$AK$3:$AL$7,2) -> Other | K3: =RANDBETWEEN(0,4) -> 3 | L3: =RANDBETWEEN(1,2) -> 2 | M3: =RANDBETWEEN(25000,90000) -> 33303 | N3: =RANDBETWEEN(1,13) -> 9 | O3: =VLOOKUP(N3,$AN$3:$AP$15,2) -> Quebec | P3: =M3*RANDBETWEEN(4,6) -> 133212 | Q3: =RAND()*P3 -> 104353.64 | R3: =L3*RAND()*M3 -> 3973.536 | S3: =RANDBETWEEN(0,R3) -> 2196 | T3: =M3*RAND()*2 -> 13206.182 | U3: =RAND()*M3*1.5 -> 17642.517 | V3: =P3+R3+U3 -> 154828.05 | W3: =Q3+S3+T3 -> 119755.82 | Z3: =IF(E3="male",1,0) -> 1 | AA3: =IF(E3="male",0,1) -> 0 | AB3: =SUM(Z3:Z500) -> 235 | AC3: =SUM(AA3:AA500) -> 263 | AG3: =COUNTIF(Table1[Field of Work],"Teaching") -> 81 | AH3: =COUNTIF(Table1[Field of Work],"Health") -> 71 | AI3: 1 | AJ3: Health | AK3: 1 | AL3: High School | AN3: 1 | AO3: Yukon | AQ3: =COUNTIF(Table1[Field of Work],"Agriculture") -> 74 | AR3: =COUNTIF(Table1[Field of Work],"IT") -> 94 | AS3: =COUNTIF(Table1[Field of Work],"Construction") -> 83 | AT3: =COUNTIF(Table1[Field of Work],"General Work") -> 95 | AV3: =AVERAGE(Table1[Income]) -> 57618.147 | AX3: =Table1[[#This Row],[Car Value]]/Table1[[#This Row],[No. of Vehicles]] -> 1986.768 | AY3: =AVERAGE(AX3:AX500) -> 28045.354 | AZ3: =IF(Table1[[#This Row],[Debts]]>$BA$3,1,0) -> 0 | BA3: =Dashboard!X14 -> 20000 | BB3: =SUM(AZ3:AZ500) -> 398 | BC3: =Table1[[#This Row],[Mortage left]]/Table1[[#This Row],[Value of The House]] -> 0.78336515 | BD3: =IF(BC3<$BE$2,1,0) -> 0 | BF3: =SUM(BD3:BD500) -> 110 | BG3: Yukon | BH3: =AVERAGEIF(Table1[Area], "Yukon", Table1[Income]) -> 59341.919 | BJ3: Health | BK3: =AVERAGEIF(Table1[Field of Work],"Health",Table1[Income]) -> 55021.986 | BM3: =COUNTIFS(Table1[Debts], ">" & Table1[Income]) / COUNTA(Table1[Income]) * 100 -> 66.465863 | BO3: =AVERAGEIFS(Table1[Age], Table1[Net Worth], ">" & $BP$3) -> 34.732932 | BP3: =Dashboard!AB14 -> 50000
D4: =RANDBETWEEN(1,2) -> 2 | E4: =IF(D4=1,"Male","Female") -> Female | F4: =RANDBETWEEN(25,45) -> 32 | G4: =RANDBETWEEN(1,6) -> 5 | H4: =VLOOKUP(G4,$AI$3:$AJ$8,2) -> Agriculture | I4: =RANDBETWEEN(1,5) -> 4 | J4: =+VLOOKUP(I4,$AK$3:$AL$7,2) -> Technical | K4: =RANDBETWEEN(0,4) -> 0 | L4: =RANDBETWEEN(1,2) -> 1 | M4: =RANDBETWEEN(25000,90000) -> 66486 | N4: =RANDBETWEEN(1,13) -> 4 | O4: =VLOOKUP(N4,$AN$3:$AP$15,2) -> Alberta | P4: =M4*RANDBETWEEN(4,6) -> 398916 | Q4: =RAND()*P4 -> 338442.39 | R4: =L4*RAND()*M4 -> 23377.547 | S4: =RANDBETWEEN(0,R4) -> 2560 | T4: =M4*RAND()*2 -> 18123.401 | U4: =RAND()*M4*1.5 -> 82408.028 | V4: =P4+R4+U4 -> 504701.57 | W4: =Q4+S4+T4 -> 359125.79 | Z4: =IF(E4="male",1,0) -> 0 | AA4: =IF(E4="male",0,1) -> 1 | AI4: 2 | AJ4: Construction | AK4: 2 | AL4: College | AN4: 2 | AO4: BC | AX4: =Table1[[#This Row],[Car Value]]/Table1[[#This Row],[No. of Vehicles]] -> 23377.547 | AZ4: =IF(Table1[[#This Row],[Debts]]>$BA$3,1,0) -> 0 | BC4: =Table1[[#This Row],[Mortage left]]/Table1[[#This Row],[Value of The House]] -> 0.84840515 | BD4: =IF(BC4<$BE$2,1,0) -> 0 | BG4: BC | BH4: =AVERAGEIF(Table1[Area], "BC", Table1[Income]) -> 60571.184 | BJ4: Construction | BK4: =AVERAGEIF(Table1[Field of Work],"Construction",Table1[Income]) -> 55980.892
D5: =RANDBETWEEN(1,2) -> 1 | E5: =IF(D5=1,"Male","Female") -> Male | F5: =RANDBETWEEN(25,45) -> 36 | G5: =RANDBETWEEN(1,6) -> 2 | H5: =VLOOKUP(G5,$AI$3:$AJ$8,2) -> Construction | I5: =RANDBETWEEN(1,5) -> 5 | J5: =+VLOOKUP(I5,$AK$3:$AL$7,2) -> Other | K5: =RANDBETWEEN(0,4) -> 2 | L5: =RANDBETWEEN(1,2) -> 2 | M5: =RANDBETWEEN(25000,90000) -> 76169 | N5: =RANDBETWEEN(1,13) -> 6 | O5: =VLOOKUP(N5,$AN$3:$AP$15,2) -> Saskatchewan | P5: =M5*RANDBETWEEN(4,6) -> 304676 | Q5: =RAND()*P5 -> 241528.87 | R5: =L5*RAND()*M5 -> 39333.118 | S5: =RANDBETWEEN(0,R5) -> 3190 | T5: =M5*RAND()*2 -> 102899.02 | U5: =RAND()*M5*1.5 -> 58611.78 | V5: =P5+R5+U5 -> 402620.9 | W5: =Q5+S5+T5 -> 347617.89 | Z5: =IF(E5="male",1,0) -> 1 | AA5: =IF(E5="male",0,1) -> 0 | AI5: 3 | AJ5: Teaching | AK5: 3 | AL5: University | AN5: 3 | AO5: Northwest Ter | AX5: =Table1[[#This Row],[Car Value]]/Table1[[#This Row],[No. of Vehicles]] -> 19666.559 | AZ5: =IF(Table1[[#This Row],[Debts]]>$BA$3,1,0) -> 1 | BC5: =Table1[[#This Row],[Mortage left]]/Table1[[#This Row],[Value of The House]] -> 0.79274005 | BD5: =IF(BC5<$BE$2,1,0) -> 0 | BG5: Northwest Ter | BH5: =AVERAGEIF(Table1[Area], "Northwest Ter", Table1[Income]) -> 56748.488 | BJ5: Teaching | BK5: =AVERAGEIF(Table1[Field of Work],"Teaching",Table1[Income]) -> 60813.012
D6: =RANDBETWEEN(1,2) -> 1 | E6: =IF(D6=1,"Male","Female") -> Male | F6: =RANDBETWEEN(25,45) -> 38 | G6: =RANDBETWEEN(1,6) -> 4 | H6: =VLOOKUP(G6,$AI$3:$AJ$8,2) -> IT | I6: =RANDBETWEEN(1,5) -> 5 | J6: =+VLOOKUP(I6,$AK$3:$AL$7,2) -> Other | K6: =RANDBETWEEN(0,4) -> 4 | L6: =RANDBETWEEN(1,2) -> 1 | M6: =RANDBETWEEN(25000,90000) -> 56921 | N6: =RANDBETWEEN(1,13) -> 6 | O6: =VLOOKUP(N6,$AN$3:$AP$15,2) -> Saskatchewan | P6: =M6*RANDBETWEEN(4,6) -> 227684 | Q6: =RAND()*P6 -> 143505.34 | R6: =L6*RAND()*M6 -> 33611.402 | S6: =RANDBETWEEN(0,R6) -> 20969 | T6: =M6*RAND()*2 -> 51806.372 | U6: =RAND()*M6*1.5 -> 6047.1195 | V6: =P6+R6+U6 -> 267342.52 | W6: =Q6+S6+T6 -> 216280.72 | Z6: =IF(E6="male",1,0) -> 1 | AA6: =IF(E6="male",0,1) -> 0 | AI6: 4 | AJ6: IT | AK6: 4 | AL6: Technical | AN6: 4 | AO6: Alberta | AX6: =Table1[[#This Row],[Car Value]]/Table1[[#This Row],[No. of Vehicles]] -> 33611.402 | AZ6: =IF(Table1[[#This Row],[Debts]]>$BA$3,1,0) -> 1 | BC6: =Table1[[#This Row],[Mortage left]]/Table1[[#This Row],[Value of The House]] -> 0.63028296 | BD6: =IF(BC6<$BE$2,1,0) -> 0 | BG6: Alberta | BH6: =AVERAGEIF(Table1[Area], "Alberta", Table1[Income]) -> 59270.676 | BJ6: IT | BK6: =AVERAGEIF(Table1[Field of Work],"IT",Table1[Income]) -> 57357.862
D7: =RANDBETWEEN(1,2) -> 2 | E7: =IF(D7=1,"Male","Female") -> Female | F7: =RANDBETWEEN(25,45) -> 25 | G7: =RANDBETWEEN(1,6) -> 4 | H7: =VLOOKUP(G7,$AI$3:$AJ$8,2) -> IT | I7: =RANDBETWEEN(1,5) -> 1 | J7: =+VLOOKUP(I7,$AK$3:$AL$7,2) -> High School | K7: =RANDBETWEEN(0,4) -> 3 | L7: =RANDBETWEEN(1,2) -> 1 | M7: =RANDBETWEEN(25000,90000) -> 39774 | N7: =RANDBETWEEN(1,13) -> 11 | O7: =VLOOKUP(N7,$AN$3:$AP$15,2) -> New bruncwick | P7: =M7*RANDBETWEEN(4,6) -> 238644 | Q7: =RAND()*P7 -> 205965 | R7: =L7*RAND()*M7 -> 1637.1059 | S7: =RANDBETWEEN(0,R7) -> 2 | T7: =M7*RAND()*2 -> 62385.112 | U7: =RAND()*M7*1.5 -> 43387.058 | V7: =P7+R7+U7 -> 283668.16 | W7: =Q7+S7+T7 -> 268352.11 | Z7: =IF(E7="male",1,0) -> 0 | AA7: =IF(E7="male",0,1) -> 1 | AI7: 5 | AJ7: Agriculture | AK7: 5 | AL7: Other | AN7: 5 | AO7: Nunavut | AX7: =Table1[[#This Row],[Car Value]]/Table1[[#This Row],[No. of Vehicles]] -> 1637.1059 | AZ7: =IF(Table1[[#This Row],[Debts]]>$BA$3,1,0) -> 1 | BC7: =Table1[[#This Row],[Mortage left]]/Table1[[#This Row],[Value of The House]] -> 0.86306381 | BD7: =IF(BC7<$BE$2,1,0) -> 0 | BG7: Nunavut | BH7: =AVERAGEIF(Table1[Area], "Nunavut", Table1[Income]) -> 59588.545 | BJ7: Agriculture | BK7: =AVERAGEIF(Table1[Field of Work],"Agriculture",Table1[Income]) -> 60521.135
D8: =RANDBETWEEN(1,2) -> 2 | E8: =IF(D8=1,"Male","Female") -> Female | F8: =RANDBETWEEN(25,45) -> 33 | G8: =RANDBETWEEN(1,6) -> 4 | H8: =VLOOKUP(G8,$AI$3:$AJ$8,2) -> IT | I8: =RANDBETWEEN(1,5) -> 2 | J8: =+VLOOKUP(I8,$AK$3:$AL$7,2) -> College | K8: =RANDBETWEEN(0,4) -> 1 | L8: =RANDBETWEEN(1,2) -> 1 | M8: =RANDBETWEEN(25000,90000) -> 60674 | N8: =RANDBETWEEN(1,13) -> 10 | O8: =VLOOKUP(N8,$AN$3:$AP$15,2) -> Newfouland | P8: =M8*RANDBETWEEN(4,6) -> 303370 | Q8: =RAND()*P8 -> 275822.77 | R8: =L8*RAND()*M8 -> 56033.588 | S8: =RANDBETWEEN(0,R8) -> 52531 | T8: =M8*RAND()*2 -> 78248.154 | U8: =RAND()*M8*1.5 -> 72204.247 | V8: =P8+R8+U8 -> 431607.83 | W8: =Q8+S8+T8 -> 406601.92 | Z8: =IF(E8="male",1,0) -> 0 | AA8: =IF(E8="male",0,1) -> 1 | AI8: 6 | AJ8: General Work | AN8: 6 | AO8: Saskatchewan | AX8: =Table1[[#This Row],[Car Value]]/Table1[[#This Row],[No. of Vehicles]] -> 56033.588 | AZ8: =IF(Table1[[#This Row],[Debts]]>$BA$3,1,0) -> 1 | BC8: =Table1[[#This Row],[Mortage left]]/Table1[[#This Row],[Value of The House]] -> 0.90919592 | BD8: =IF(BC8<$BE$2,1,0) -> 0 | BG8: Saskatchewan | BH8: =AVERAGEIF(Table1[Area], "Saskatchewan", Table1[Income]) -> 58314.577 | BJ8: General Work | BK8: =AVERAGEIF(Table1[Field of Work],"General Work",Table1[Income]) -> 56261.105
D9: =RANDBETWEEN(1,2) -> 1 | E9: =IF(D9=1,"Male","Female") -> Male | F9: =RANDBETWEEN(25,45) -> 39 | G9: =RANDBETWEEN(1,6) -> 6 | H9: =VLOOKUP(G9,$AI$3:$AJ$8,2) -> General Work | I9: =RANDBETWEEN(1,5) -> 1 | J9: =+VLOOKUP(I9,$AK$3:$AL$7,2) -> High School | K9: =RANDBETWEEN(0,4) -> 3 | L9: =RANDBETWEEN(1,2) -> 2 | M9: =RANDBETWEEN(25000,90000) -> 76594 | N9: =RANDBETWEEN(1,13) -> 5 | O9: =VLOOKUP(N9,$AN$3:$AP$15,2) -> Nunavut | P9: =M9*RANDBETWEEN(4,6) -> 382970 | Q9: =RAND()*P9 -> 80083.457 | R9: =L9*RAND()*M9 -> 6008.8135 | S9: =RANDBETWEEN(0,R9) -> 875 | T9: =M9*RAND()*2 -> 19516.307 | U9: =RAND()*M9*1.5 -> 68543.207 | V9: =P9+R9+U9 -> 457522.02 | W9: =Q9+S9+T9 -> 100474.76 | Z9: =IF(E9="male",1,0) -> 1 | AA9: =IF(E9="male",0,1) -> 0 | AN9: 7 | AO9: Manitoba | AX9: =Table1[[#This Row],[Car Value]]/Table1[[#This Row],[No. of Vehicles]] -> 3004.4068 | AZ9: =IF(Table1[[#This Row],[Debts]]>$BA$3,1,0) -> 0 | BC9: =Table1[[#This Row],[Mortage left]]/Table1[[#This Row],[Value of The House]] -> 0.20911157 | BD9: =IF(BC9<$BE$2,1,0) -> 0 | BG9: Manitoba | BH9: =AVERAGEIF(Table1[Area], "Manitoba", Table1[Income]) -> 56639.28
D10: =RANDBETWEEN(1,2) -> 2 | E10: =IF(D10=1,"Male","Female") -> Female | F10: =RANDBETWEEN(25,45) -> 36 | G10: =RANDBETWEEN(1,6) -> 4 | H10: =VLOOKUP(G10,$AI$3:$AJ$8,2) -> IT | I10: =RANDBETWEEN(1,5) -> 3 | J10: =+VLOOKUP(I10,$AK$3:$AL$7,2) -> University | K10: =RANDBETWEEN(0,4) -> 3 | L10: =RANDBETWEEN(1,2) -> 2 | M10: =RANDBETWEEN(25000,90000) -> 44196 | N10: =RANDBETWEEN(1,13) -> 5 | O10: =VLOOKUP(N10,$AN$3:$AP$15,2) -> Nunavut | P10: =M10*RANDBETWEEN(4,6) -> 176784 | Q10: =RAND()*P10 -> 75583.946 | R10: =L10*RAND()*M10 -> 31329.589 | S10: =RANDBETWEEN(0,R10) -> 25464 | T10: =M10*RAND()*2 -> 63125.552 | U10: =RAND()*M10*1.5 -> 51222.336 | V10: =P10+R10+U10 -> 259335.92 | W10: =Q10+S10+T10 -> 164173.5 | Z10: =IF(E10="male",1,0) -> 0 | AA10: =IF(E10="male",0,1) -> 1 | AN10: 8 | AO10: Ontario | AX10: =Table1[[#This Row],[Car Value]]/Table1[[#This Row],[No. of Vehicles]] -> 15664.794 | AZ10: =IF(Table1[[#This Row],[Debts]]>$BA$3,1,0) -> 1 | BC10: =Table1[[#This Row],[Mortage left]]/Table1[[#This Row],[Value of The House]] -> 0.4275497 | BD10: =IF(BC10<$BE$2,1,0) -> 0 | BG10: Ontario | BH10: =AVERAGEIF(Table1[Area], "Ontario", Table1[Income]) -> 53553.78
D11: =RANDBETWEEN(1,2) -> 2 | E11: =IF(D11=1,"Male","Female") -> Female | F11: =RANDBETWEEN(25,45) -> 31 | G11: =RANDBETWEEN(1,6) -> 6 | H11: =VLOOKUP(G11,$AI$3:$AJ$8,2) -> General Work | I11: =RANDBETWEEN(1,5) -> 1 | J11: =+VLOOKUP(I11,$AK$3:$AL$7,2) -> High School | K11: =RANDBETWEEN(0,4) -> 1 | L11: =RANDBETWEEN(1,2) -> 1 | M11: =RANDBETWEEN(25000,90000) -> 43533 | N11: =RANDBETWEEN(1,13) -> 5 | O11: =VLOOKUP(N11,$AN$3:$AP$15,2) -> Nunavut | P11: =M11*RANDBETWEEN(4,6) -> 217665 | Q11: =RAND()*P11 -> 51265.805 | R11: =L11*RAND()*M11 -> 39502.765 | S11: =RANDBETWEEN(0,R11) -> 33235 | T11: =M11*RAND()*2 -> 57105.191 | U11: =RAND()*M11*1.5 -> 18198.654 | V11: =P11+R11+U11 -> 275366.42 | W11: =Q11+S11+T11 -> 141606 | Z11: =IF(E11="male",1,0) -> 0 | AA11: =IF(E11="male",0,1) -> 1 | AN11: 9 | AO11: Quebec | AX11: =Table1[[#This Row],[Car Value]]/Table1[[#This Row],[No. of Vehicles]] -> 39502.765 | AZ11: =IF(Table1[[#This Row],[Debts]]>$BA$3,1,0) -> 1 | BC11: =Table1[[#This Row],[Mortage left]]/Table1[[#This Row],[Value of The House]] -> 0.23552618 | BD11: =IF(BC11<$BE$2,1,0) -> 0 | BG11: Quebec | BH11: =AVERAGEIF(Table1[Area], "Quebec", Table1[Income]) -> 52561.25
D12: =RANDBETWEEN(1,2) -> 2 | E12: =IF(D12=1,"Male","Female") -> Female | F12: =RANDBETWEEN(25,45) -> 33 | G12: =RANDBETWEEN(1,6) -> 3 | H12: =VLOOKUP(G12,$AI$3:$AJ$8,2) -> Teaching | I12: =RANDBETWEEN(1,5) -> 4 | J12: =+VLOOKUP(I12,$AK$3:$AL$7,2) -> Technical | K12: =RANDBETWEEN(0,4) -> 3 | L12: =RANDBETWEEN(1,2) -> 2 | M12: =RANDBETWEEN(25000,90000) -> 64180 | N12: =RANDBETWEEN(1,13) -> 12 | O12: =VLOOKUP(N12,$AN$3:$AP$15,2) -> Nova scotia | P12: =M12*RANDBETWEEN(4,6) -> 385080 | Q12: =RAND()*P12 -> 291236.66 | R12: =L12*RAND()*M12 -> 35919.188 | S12: =RANDBETWEEN(0,R12) -> 32538 | T12: =M12*RAND()*2 -> 126789.38 | U12: =RAND()*M12*1.5 -> 4187.4745 | V12: =P12+R12+U12 -> 425186.66 | W12: =Q12+S12+T12 -> 450564.04 | Z12: =IF(E12="male",1,0) -> 0 | AA12: =IF(E12="male",0,1) -> 1 | AN12: 10 | AO12: Newfouland | AX12: =Table1[[#This Row],[Car Value]]/Table1[[#This Row],[No. of Vehicles]] -> 17959.594 | AZ12: =IF(Table1[[#This Row],[Debts]]>$BA$3,1,0) -> 1 | BC12: =Table1[[#This Row],[Mortage left]]/Table1[[#This Row],[Value of The House]] -> 0.75630169 | BD12: =IF(BC12<$BE$2,1,0) -> 0 | BG12: Newfouland | BH12: =AVERAGEIF(Table1[Area], "Newfouland", Table1[Income]) -> 55601.882
D13: =RANDBETWEEN(1,2) -> 2 | E13: =IF(D13=1,"Male","Female") -> Female | F13: =RANDBETWEEN(25,45) -> 43 | G13: =RANDBETWEEN(1,6) -> 3 | H13: =VLOOKUP(G13,$AI$3:$AJ$8,2) -> Teaching | I13: =RANDBETWEEN(1,5) -> 3 | J13: =+VLOOKUP(I13,$AK$3:$AL$7,2) -> University | K13: =RANDBETWEEN(0,4) -> 4 | L13: =RANDBETWEEN(1,2) -> 1 | M13: =RANDBETWEEN(25000,90000) -> 56831 | N13: =RANDBETWEEN(1,13) -> 9 | O13: =VLOOKUP(N13,$AN$3:$AP$15,2) -> Quebec | P13: =M13*RANDBETWEEN(4,6) -> 284155 | Q13: =RAND()*P13 -> 147087.03 | R13: =L13*RAND()*M13 -> 9933.8445 | S13: =RANDBETWEEN(0,R13) -> 9166 | T13: =M13*RAND()*2 -> 15535.743 | U13: =RAND()*M13*1.5 -> 46302.018 | V13: =P13+R13+U13 -> 340390.86 | W13: =Q13+S13+T13 -> 171788.77 | Z13: =IF(E13="male",1,0) -> 0 | AA13: =IF(E13="male",0,1) -> 1 | AN13: 11 | AO13: New bruncwick | AX13: =Table1[[#This Row],[Car Value]]/Table1[[#This Row],[No. of Vehicles]] -> 9933.8445 | AZ13: =IF(Table1[[#This Row],[Debts]]>$BA$3,1,0) -> 0 | BC13: =Table1[[#This Row],[Mortage left]]/Table1[[#This Row],[Value of The House]] -> 0.51762957 | BD13: =IF(BC13<$BE$2,1,0) -> 0 | BG13: New brunswick | BH13: =AVERAGEIF(Table1[Area], "New bruncwick", Table1[Income]) -> 58167.925
D14: =RANDBETWEEN(1,2) -> 1 | E14: =IF(D14=1,"Male","Female") -> Male | F14: =RANDBETWEEN(25,45) -> 40 | G14: =RANDBETWEEN(1,6) -> 1 | H14: =VLOOKUP(G14,$AI$3:$AJ$8,2) -> Health | I14: =RANDBETWEEN(1,5) -> 5 | J14: =+VLOOKUP(I14,$AK$3:$AL$7,2) -> Other | K14: =RANDBETWEEN(0,4) -> 2 | L14: =RANDBETWEEN(1,2) -> 2 | M14: =RANDBETWEEN(25000,90000) -> 76455 | N14: =RANDBETWEEN(1,13) -> 3 | O14: =VLOOKUP(N14,$AN$3:$AP$15,2) -> Northwest Ter | P14: =M14*RANDBETWEEN(4,6) -> 458730 | Q14: =RAND()*P14 -> 326116.56 | R14: =L14*RAND()*M14 -> 80358.751 | S14: =RANDBETWEEN(0,R14) -> 7692 | T14: =M14*RAND()*2 -> 24480.772 | U14: =RAND()*M14*1.5 -> 88048.158 | V14: =P14+R14+U14 -> 627136.91 | W14: =Q14+S14+T14 -> 358289.34 | Z14: =IF(E14="male",1,0) -> 1 | AA14: =IF(E14="male",0,1) -> 0 | AN14: 12 | AO14: Nova scotia | AX14: =Table1[[#This Row],[Car Value]]/Table1[[#This Row],[No. of Vehicles]] -> 40179.375 | AZ14: =IF(Table1[[#This Row],[Debts]]>$BA$3,1,0) -> 1 | BC14: =Table1[[#This Row],[Mortage left]]/Table1[[#This Row],[Value of The House]] -> 0.71091179 | BD14: =IF(BC14<$BE$2,1,0) -> 0 | BG14: Nova Scotia | BH14: =AVERAGEIF(Table1[Area], "Nova scotia", Table1[Income]) -> 55032.455
D15: =RANDBETWEEN(1,2) -> 1 | E15: =IF(D15=1,"Male","Female") -> Male | F15: =RANDBETWEEN(25,45) -> 38 | G15: =RANDBETWEEN(1,6) -> 5 | H15: =VLOOKUP(G15,$AI$3:$AJ$8,2) -> Agriculture | I15: =RANDBETWEEN(1,5) -> 2 | J15: =+VLOOKUP(I15,$AK$3:$AL$7,2) -> College | K15: =RANDBETWEEN(0,4) -> 3 | L15: =RANDBETWEEN(1,2) -> 1 | M15: =RANDBETWEEN(25000,90000) -> 69441 | N15: =RANDBETWEEN(1,13) -> 6 | O15: =VLOOKUP(N15,$AN$3:$AP$15,2) -> Saskatchewan | P15: =M15*RANDBETWEEN(4,6) -> 416646 | Q15: =RAND()*P15 -> 34967.354 | R15: =L15*RAND()*M15 -> 63053.98 | S15: =RANDBETWEEN(0,R15) -> 50681 | T15: =M15*RAND()*2 -> 74942.032 | U15: =RAND()*M15*1.5 -> 21818.526 | V15: =P15+R15+U15 -> 501518.51 | W15: =Q15+S15+T15 -> 160590.39 | Z15: =IF(E15="male",1,0) -> 1 | AA15: =IF(E15="male",0,1) -> 0 | AN15: 13 | AO15: Prince Edward Islnd | AX15: =Table1[[#This Row],[Car Value]]/Table1[[#This Row],[No. of Vehicles]] -> 63053.98 | AZ15: =IF(Table1[[#This Row],[Debts]]>$BA$3,1,0) -> 1 | BC15: =Table1[[#This Row],[Mortage left]]/Table1[[#This Row],[Value of The House]] -> 0.083925811 | BD15: =IF(BC15<$BE$2,1,0) -> 1 | BG15: Prince Edward Island | BH15: =AVERAGEIF(Table1[Area], "Prince Edward Islnd", Table1[Income]) -> 61583.062
D16: =RANDBETWEEN(1,2) -> 1 | E16: =IF(D16=1,"Male","Female") -> Male | F16: =RANDBETWEEN(25,45) -> 30 | G16: =RANDBETWEEN(1,6) -> 1 | H16: =VLOOKUP(G16,$AI$3:$AJ$8,2) -> Health | I16: =RANDBETWEEN(1,5) -> 4 | J16: =+VLOOKUP(I16,$AK$3:$AL$7,2) -> Technical | K16: =RANDBETWEEN(0,4) -> 0 | L16: =RANDBETWEEN(1,2) -> 2 | M16: =RANDBETWEEN(25000,90000) -> 69197 | N16: =RANDBETWEEN(1,13) -> 12 | O16: =VLOOKUP(N16,$AN$3:$AP$15,2) -> Nova scotia | P16: =M16*RANDBETWEEN(4,6) -> 415182 | Q16: =RAND()*P16 -> 85897.096 | R16: =L16*RAND()*M16 -> 87626.631 | S16: =RANDBETWEEN(0,R16) -> 23334 | T16: =M16*RAND()*2 -> 5334.4193 | U16: =RAND()*M16*1.5 -> 74487.213 | V16: =P16+R16+U16 -> 577295.84 | W16: =Q16+S16+T16 -> 114565.52 | Z16: =IF(E16="male",1,0) -> 1 | AA16: =IF(E16="male",0,1) -> 0 | AX16: =Table1[[#This Row],[Car Value]]/Table1[[#This Row],[No. of Vehicles]] -> 43813.316 | AZ16: =IF(Table1[[#This Row],[Debts]]>$BA$3,1,0) -> 0 | BC16: =Table1[[#This Row],[Mortage left]]/Table1[[#This Row],[Value of The House]] -> 0.20689022 | BD16: =IF(BC16<$BE$2,1,0) -> 0
D17: =RANDBETWEEN(1,2) -> 2 | E17: =IF(D17=1,"Male","Female") -> Female | F17: =RANDBETWEEN(25,45) -> 41 | G17: =RANDBETWEEN(1,6) -> 2 | H17: =VLOOKUP(G17,$AI$3:$AJ$8,2) -> Construction | I17: =RANDBETWEEN(1,5) -> 3 | J17: =+VLOOKUP(I17,$AK$3:$AL$7,2) -> University | K17: =RANDBETWEEN(0,4) -> 3 | L17: =RANDBETWEEN(1,2) -> 2 | M17: =RANDBETWEEN(25000,90000) -> 49302 | N17: =RANDBETWEEN(1,13) -> 8 | O17: =VLOOKUP(N17,$AN$3:$AP$15,2) -> Ontario | P17: =M17*RANDBETWEEN(4,6) -> 295812 | Q17: =RAND()*P17 -> 71582.178 | R17: =L17*RAND()*M17 -> 53916.113 | S17: =RANDBETWEEN(0,R17) -> 47912 | T17: =M17*RAND()*2 -> 33843.248 | U17: =RAND()*M17*1.5 -> 33235.774 | V17: =P17+R17+U17 -> 382963.89 | W17: =Q17+S17+T17 -> 153337.43 | Z17: =IF(E17="male",1,0) -> 0 | AA17: =IF(E17="male",0,1) -> 1 | AX17: =Table1[[#This Row],[Car Value]]/Table1[[#This Row],[No. of Vehicles]] -> 26958.057 | AZ17: =IF(Table1[[#This Row],[Debts]]>$BA$3,1,0) -> 1 | BC17: =Table1[[#This Row],[Mortage left]]/Table1[[#This Row],[Value of The House]] -> 0.24198537 | BD17: =IF(BC17<$BE$2,1,0) -> 0
D18: =RANDBETWEEN(1,2) -> 1 | E18: =IF(D18=1,"Male","Female") -> Male | F18: =RANDBETWEEN(25,45) -> 45 | G18: =RANDBETWEEN(1,6) -> 1 | H18: =VLOOKUP(G18,$AI$3:$AJ$8,2) -> Health | I18: =RANDBETWEEN(1,5) -> 4 | J18: =+VLOOKUP(I18,$AK$3:$AL$7,2) -> Technical | K18: =RANDBETWEEN(0,4) -> 4 | L18: =RANDBETWEEN(1,2) -> 2 | M18: =RANDBETWEEN(25000,90000) -> 46322 | N18: =RANDBETWEEN(1,13) -> 11 | O18: =VLOOKUP(N18,$AN$3:$AP$15,2) -> New bruncwick | P18: =M18*RANDBETWEEN(4,6) -> 185288 | Q18: =RAND()*P18 -> 46413.56 | R18: =L18*RAND()*M18 -> 47001.143 | S18: =RANDBETWEEN(0,R18) -> 1337 | T18: =M18*RAND()*2 -> 46969.201 | U18: =RAND()*M18*1.5 -> 41574.952 | V18: =P18+R18+U18 -> 273864.09 | W18: =Q18+S18+T18 -> 94719.761 | Z18: =IF(E18="male",1,0) -> 1 | AA18: =IF(E18="male",0,1) -> 0 | AX18: =Table1[[#This Row],[Car Value]]/Table1[[#This Row],[No. of Vehicles]] -> 23500.571 | AZ18: =IF(Table1[[#This Row],[Debts]]>$BA$3,1,0) -> 1 | BC18: =Table1[[#This Row],[Mortage left]]/Table1[[#This Row],[Value of The House]] -> 0.25049415 | BD18: =IF(BC18<$BE$2,1,0) -> 0
D19: =RANDBETWEEN(1,2) -> 2 | E19: =IF(D19=1,"Male","Female") -> Female | F19: =RANDBETWEEN(25,45) -> 33 | G19: =RANDBETWEEN(1,6) -> 4 | H19: =VLOOKUP(G19,$AI$3:$AJ$8,2) -> IT | I19: =RANDBETWEEN(1,5) -> 3 | J19: =+VLOOKUP(I19,$AK$3:$AL$7,2) -> University | K19: =RANDBETWEEN(0,4) -> 2 | L19: =RANDBETWEEN(1,2) -> 2 | M19: =RANDBETWEEN(25000,90000) -> 84112 | N19: =RANDBETWEEN(1,13) -> 1 | O19: =VLOOKUP(N19,$AN$3:$AP$15,2) -> Yukon | P19: =M19*RANDBETWEEN(4,6) -> 504672 | Q19: =RAND()*P19 -> 279877.84 | R19: =L19*RAND()*M19 -> 4707.3167 | S19: =RANDBETWEEN(0,R19) -> 3923 | T19: =M19*RAND()*2 -> 51366.846 | U19: =RAND()*M19*1.5 -> 51151.442 | V19: =P19+R19+U19 -> 560530.76 | W19: =Q19+S19+T19 -> 335167.69 | Z19: =IF(E19="male",1,0) -> 0 | AA19: =IF(E19="male",0,1) -> 1 | AX19: =Table1[[#This Row],[Car Value]]/Table1[[#This Row],[No. of Vehicles]] -> 2353.6583 | AZ19: =IF(Table1[[#This Row],[Debts]]>$BA$3,1,0) -> 1 | BC19: =Table1[[#This Row],[Mortage left]]/Table1[[#This Row],[Value of The House]] -> 0.55457375 | BD19: =IF(BC19<$BE$2,1,0) -> 0
D20: =RANDBETWEEN(1,2) -> 1 | E20: =IF(D20=1,"Male","Female") -> Male | F20: =RANDBETWEEN(25,45) -> 44 | G20: =RANDBETWEEN(1,6) -> 4 | H20: =VLOOKUP(G20,$AI$3:$AJ$8,2) -> IT | I20: =RANDBETWEEN(1,5) -> 2 | J20: =+VLOOKUP(I20,$AK$3:$AL$7,2) -> College | K20: =RANDBETWEEN(0,4) -> 2 | L20: =RANDBETWEEN(1,2) -> 1 | M20: =RANDBETWEEN(25000,90000) -> 26203 | N20: =RANDBETWEEN(1,13) -> 1 | O20: =VLOOKUP(N20,$AN$3:$AP$15,2) -> Yukon | P20: =M20*RANDBETWEEN(4,6) -> 157218 | Q20: =RAND()*P20 -> 5017.8157 | R20: =L20*RAND()*M20 -> 11169.139 | S20: =RANDBETWEEN(0,R20) -> 10953 | T20: =M20*RAND()*2 -> 37670.479 | U20: =RAND()*M20*1.5 -> 38429.766 | V20: =P20+R20+U20 -> 206816.91 | W20: =Q20+S20+T20 -> 53641.295 | Z20: =IF(E20="male",1,0) -> 1 | AA20: =IF(E20="male",0,1) -> 0 | AX20: =Table1[[#This Row],[Car Value]]/Table1[[#This Row],[No. of Vehicles]] -> 11169.139 | AZ20: =IF(Table1[[#This Row],[Debts]]>$BA$3,1,0) -> 1 | BC20: =Table1[[#This Row],[Mortage left]]/Table1[[#This Row],[Value of The House]] -> 0.031916293 | BD20: =IF(BC20<$BE$2,1,0) -> 1
D21: =RANDBETWEEN(1,2) -> 1 | E21: =IF(D21=1,"Male","Female") -> Male | F21: =RANDBETWEEN(25,45) -> 29 | G21: =RANDBETWEEN(1,6) -> 4 | H21: =VLOOKUP(G21,$AI$3:$AJ$8,2) -> IT | I21: =RANDBETWEEN(1,5) -> 2 | J21: =+VLOOKUP(I21,$AK$3:$AL$7,2) -> College | K21: =RANDBETWEEN(0,4) -> 3 | L21: =RANDBETWEEN(1,2) -> 2 | M21: =RANDBETWEEN(25000,90000) -> 46767 | N21: =RANDBETWEEN(1,13) -> 3 | O21: =VLOOKUP(N21,$AN$3:$AP$15,2) -> Northwest Ter | P21: =M21*RANDBETWEEN(4,6) -> 187068 | Q21: =RAND()*P21 -> 80652.043 | R21: =L21*RAND()*M21 -> 3875.0505 | S21: =RANDBETWEEN(0,R21) -> 3281 | T21: =M21*RAND()*2 -> 41669.545 | U21: =RAND()*M21*1.5 -> 20190.078 | V21: =P21+R21+U21 -> 211133.13 | W21: =Q21+S21+T21 -> 125602.59 | Z21: =IF(E21="male",1,0) -> 1 | AA21: =IF(E21="male",0,1) -> 0 | AX21: =Table1[[#This Row],[Car Value]]/Table1[[#This Row],[No. of Vehicles]] -> 1937.5252 | AZ21: =IF(Table1[[#This Row],[Debts]]>$BA$3,1,0) -> 1 | BC21: =Table1[[#This Row],[Mortage left]]/Table1[[#This Row],[Value of The House]] -> 0.43113757 | BD21: =IF(BC21<$BE$2,1,0) -> 0
D22: =RANDBETWEEN(1,2) -> 2 | E22: =IF(D22=1,"Male","Female") -> Female | F22: =RANDBETWEEN(25,45) -> 32 | G22: =RANDBETWEEN(1,6) -> 4 | H22: =VLOOKUP(G22,$AI$3:$AJ$8,2) -> IT | I22: =RANDBETWEEN(1,5) -> 2 | J22: =+VLOOKUP(I22,$AK$3:$AL$7,2) -> College | K22: =RANDBETWEEN(0,4) -> 2 | L22: =RANDBETWEEN(1,2) -> 1 | M22: =RANDBETWEEN(25000,90000) -> 52579 | N22: =RANDBETWEEN(1,13) -> 5 | O22: =VLOOKUP(N22,$AN$3:$AP$15,2) -> Nunavut | P22: =M22*RANDBETWEEN(4,6) -> 262895 | Q22: =RAND()*P22 -> 212598.37 | R22: =L22*RAND()*M22 -> 8474.2356 | S22: =RANDBETWEEN(0,R22) -> 4135 | T22: =M22*RAND()*2 -> 10930.284 | U22: =RAND()*M22*1.5 -> 62854.113 | V22: =P22+R22+U22 -> 334223.35 | W22: =Q22+S22+T22 -> 227663.65 | Z22: =IF(E22="male",1,0) -> 0 | AA22: =IF(E22="male",0,1) -> 1 | AX22: =Table1[[#This Row],[Car Value]]/Table1[[#This Row],[No. of Vehicles]] -> 8474.2356 | AZ22: =IF(Table1[[#This Row],[Debts]]>$BA$3,1,0) -> 0 | BC22: =Table1[[#This Row],[Mortage left]]/Table1[[#This Row],[Value of The House]] -> 0.80868166 | BD22: =IF(BC22<$BE$2,1,0) -> 0
D23: =RANDBETWEEN(1,2) -> 2 | E23: =IF(D23=1,"Male","Female") -> Female | F23: =RANDBETWEEN(25,45) -> 44 | G23: =RANDBETWEEN(1,6) -> 2 | H23: =VLOOKUP(G23,$AI$3:$AJ$8,2) -> Construction | I23: =RANDBETWEEN(1,5) -> 4 | J23: =+VLOOKUP(I23,$AK$3:$AL$7,2) -> Technical | K23: =RANDBETWEEN(0,4) -> 1 | L23: =RANDBETWEEN(1,2) -> 1 | M23: =RANDBETWEEN(25000,90000) -> 69261 | N23: =RANDBETWEEN(1,13) -> 12 | O23: =VLOOKUP(N23,$AN$3:$AP$15,2) -> Nova scotia | P23: =M23*RANDBETWEEN(4,6) -> 346305 | Q23: =RAND()*P23 -> 102986.14 | R23: =L23*RAND()*M23 -> 25878.155 | S23: =RANDBETWEEN(0,R23) -> 13995 | T23: =M23*RAND()*2 -> 6965.7897 | U23: =RAND()*M23*1.5 -> 44431.823 | V23: =P23+R23+U23 -> 416614.98 | W23: =Q23+S23+T23 -> 123946.93 | Z23: =IF(E23="male",1,0) -> 0 | AA23: =IF(E23="male",0,1) -> 1 | AX23: =Table1[[#This Row],[Car Value]]/Table1[[#This Row],[No. of Vehicles]] -> 25878.155 | AZ23: =IF(Table1[[#This Row],[Debts]]>$BA$3,1,0) -> 0 | BC23: =Table1[[#This Row],[Mortage left]]/Table1[[#This Row],[Value of The House]] -> 0.29738567 | BD23: =IF(BC23<$BE$2,1,0) -> 0
D24: =RANDBETWEEN(1,2) -> 1 | E24: =IF(D24=1,"Male","Female") -> Male | F24: =RANDBETWEEN(25,45) -> 32 | G24: =RANDBETWEEN(1,6) -> 4 | H24: =VLOOKUP(G24,$AI$3:$AJ$8,2) -> IT | I24: =RANDBETWEEN(1,5) -> 2 | J24: =+VLOOKUP(I24,$AK$3:$AL$7,2) -> College | K24: =RANDBETWEEN(0,4) -> 3 | L24: =RANDBETWEEN(1,2) -> 1 | M24: =RANDBETWEEN(25000,90000) -> 67732 | N24: =RANDBETWEEN(1,13) -> 12 | O24: =VLOOKUP(N24,$AN$3:$AP$15,2) -> Nova scotia | P24: =M24*RANDBETWEEN(4,6) -> 406392 | Q24: =RAND()*P24 -> 59597.534 | R24: =L24*RAND()*M24 -> 39818.145 | S24: =RANDBETWEEN(0,R24) -> 32853 | T24: =M24*RAND()*2 -> 52647.263 | U24: =RAND()*M24*1.5 -> 30490.498 | V24: =P24+R24+U24 -> 476700.64 | W24: =Q24+S24+T24 -> 145097.8 | Z24: =IF(E24="male",1,0) -> 1 | AA24: =IF(E24="male",0,1) -> 0 | AX24: =Table1[[#This Row],[Car Value]]/Table1[[#This Row],[No. of Vehicles]] -> 39818.145 | AZ24: =IF(Table1[[#This Row],[Debts]]>$BA$3,1,0) -> 1 | BC24: =Table1[[#This Row],[Mortage left]]/Table1[[#This Row],[Value of The House]] -> 0.14665036 | BD24: =IF(BC24<$BE$2,1,0) -> 1
D25: =RANDBETWEEN(1,2) -> 1 | E25: =IF(D25=1,"Male","Female") -> Male | F25: =RANDBETWEEN(25,45) -> 35 | G25: =RANDBETWEEN(1,6) -> 1 | H25: =VLOOKUP(G25,$AI$3:$AJ$8,2) -> Health | I25: =RANDBETWEEN(1,5) -> 5 | J25: =+VLOOKUP(I25,$AK$3:$AL$7,2) -> Other | K25: =RANDBETWEEN(0,4) -> 4 | L25: =RANDBETWEEN(1,2) -> 1 | M25: =RANDBETWEEN(25000,90000) -> 57569 | N25: =RANDBETWEEN(1,13) -> 11 | O25: =VLOOKUP(N25,$AN$3:$AP$15,2) -> New bruncwick | P25: =M25*RANDBETWEEN(4,6) -> 230276 | Q25: =RAND()*P25 -> 120252.69 | R25: =L25*RAND()*M25 -> 17873.228 | S25: =RANDBETWEEN(0,R25) -> 12062 | T25: =M25*RAND()*2 -> 50363.757 | U25: =RAND()*M25*1.5 -> 52652.724 | V25: =P25+R25+U25 -> 300801.95 | W25: =Q25+S25+T25 -> 182678.44 | Z25: =IF(E25="male",1,0) -> 1 | AA25: =IF(E25="male",0,1) -> 0 | AX25: =Table1[[#This Row],[Car Value]]/Table1[[#This Row],[No. of Vehicles]] -> 17873.228 | AZ25: =IF(Table1[[#This Row],[Debts]]>$BA$3,1,0) -> 1 | BC25: =Table1[[#This Row],[Mortage left]]/Table1[[#This Row],[Value of The House]] -> 0.52221112 | BD25: =IF(BC25<$BE$2,1,0) -> 0
D26: =RANDBETWEEN(1,2) -> 2 | E26: =IF(D26=1,"Male","Female") -> Female | F26: =RANDBETWEEN(25,45) -> 41 | G26: =RANDBETWEEN(1,6) -> 2 | H26: =VLOOKUP(G26,$AI$3:$AJ$8,2) -> Construction | I26: =RANDBETWEEN(1,5) -> 3 | J26: =+VLOOKUP(I26,$AK$3:$AL$7,2) -> University | K26: =RANDBETWEEN(0,4) -> 3 | L26: =RANDBETWEEN(1,2) -> 1 | M26: =RANDBETWEEN(25000,90000) -> 69683 | N26: =RANDBETWEEN(1,13) -> 8 | O26: =VLOOKUP(N26,$AN$3:$AP$15,2) -> Ontario | P26: =M26*RANDBETWEEN(4,6) -> 278732 | Q26: =RAND()*P26 -> 254636.6 | R26: =L26*RAND()*M26 -> 51950.239 | S26: =RANDBETWEEN(0,R26) -> 25857 | T26: =M26*RAND()*2 -> 39548.552 | U26: =RAND()*M26*1.5 -> 76081.11 | V26: =P26+R26+U26 -> 406763.35 | W26: =Q26+S26+T26 -> 320042.16 | Z26: =IF(E26="male",1,0) -> 0 | AA26: =IF(E26="male",0,1) -> 1 | AX26: =Table1[[#This Row],[Car Value]]/Table1[[#This Row],[No. of Vehicles]] -> 51950.239 | AZ26: =IF(Table1[[#This Row],[Debts]]>$BA$3,1,0) -> 1 | BC26: =Table1[[#This Row],[Mortage left]]/Table1[[#This Row],[Value of The House]] -> 0.91355354 | BD26: =IF(BC26<$BE$2,1,0) -> 0
D27: =RANDBETWEEN(1,2) -> 2 | E27: =IF(D27=1,"Male","Female") -> Female | F27: =RANDBETWEEN(25,45) -> 29 | G27: =RANDBETWEEN(1,6) -> 5 | H27: =VLOOKUP(G27,$AI$3:$AJ$8,2) -> Agriculture | I27: =RANDBETWEEN(1,5) -> 1 | J27: =+VLOOKUP(I27,$AK$3:$AL$7,2) -> High School | K27: =RANDBETWEEN(0,4) -> 2 | L27: =RANDBETWEEN(1,2) -> 1 | M27: =RANDBETWEEN(25000,90000) -> 37882 | N27: =RANDBETWEEN(1,13) -> 12 | O27: =VLOOKUP(N27,$AN$3:$AP$15,2) -> Nova scotia | P27: =M27*RANDBETWEEN(4,6) -> 189410 | Q27: =RAND()*P27 -> 136731.58 | R27: =L27*RAND()*M27 -> 21328.96 | S27: =RANDBETWEEN(0,R27) -> 3810 | T27: =M27*RAND()*2 -> 64990.642 | U27: =RAND()*M27*1.5 -> 47223.317 | V27: =P27+R27+U27 -> 257962.28 | W27: =Q27+S27+T27 -> 205532.22 | Z27: =IF(E27="male",1,0) -> 0 | AA27: =IF(E27="male",0,1) -> 1 | AX27: =Table1[[#This Row],[Car Value]]/Table1[[#This Row],[No. of Vehicles]] -> 21328.96 | AZ27: =IF(Table1[[#This Row],[Debts]]>$BA$3,1,0) -> 1 | BC27: =Table1[[#This Row],[Mortage left]]/Table1[[#This Row],[Value of The House]] -> 0.72188154 | BD27: =IF(BC27<$BE$2,1,0) -> 0
... D500: =RANDBETWEEN(1,2) -> 1 | E500: =IF(D500=1,"Male","Female") -> Male | F500: =RANDBETWEEN(25,45) -> 43 | G500: =RANDBETWEEN(1,6) -> 1 | H500: =VLOOKUP(G500,$AI$3:$AJ$8,2) -> Health | I500: =RANDBETWEEN(1,5) -> 2 | J500: =+VLOOKUP(I500,$AK$3:$AL$7,2) -> College | K500: =RANDBETWEEN(0,4) -> 2 | L500: =RANDBETWEEN(1,2) -> 2 | M500: =RANDBETWEEN(25000,90000) -> 30826 | N500: =RANDBETWEEN(1,13) -> 9 | O500: =VLOOKUP(N500,$AN$3:$AP$15,2) -> Quebec | P500: =M500*RANDBETWEEN(4,6) -> 154130 | Q500: =RAND()*P500 -> 63642.16 | R500: =L500*RAND()*M500 -> 3741.0995 | S500: =RANDBETWEEN(0,R500) -> 2034 | T500: =M500*RAND()*2 -> 15499.761 | U500: =RAND()*M500*1.5 -> 37831.676 | V500: =P500+R500+U500 -> 195702.78 | W500: =Q500+S500+T500 -> 81175.92 | Z500: =IF(E500="male",1,0) -> 1 | AA500: =IF(E500="male",0,1) -> 0 | AX500: =Table1[[#This Row],[Car Value]]/Table1[[#This Row],[No. of Vehicles]] -> 1870.5498 | AZ500: =IF(Table1[[#This Row],[Debts]]>$BA$3,1,0) -> 0 | BC500: =Table1[[#This Row],[Mortage left]]/Table1[[#This Row],[Value of The House]] -> 0.41291222 | BD500: =IF(BC500<$BE$2,1,0) -> 0

Sheet Dashboard
D4: Basic
D6: Number of Male Vs Number Female | H6: Average Age | L6: Number of People in each Profession
L7: Teaching | N7: Health | P7: Agriculture | R7: IT | T7: Construction | V7: General Work
D8: Male | F8: Female | H8: =Sheet1!AE2 -> 34.732932 | L8: =Sheet1!AG3 -> 81 | N8: =Sheet1!AH3 -> 71 | P8: =Sheet1!AQ3 -> 74 | R8: =Sheet1!AR3 -> 94 | T8: =Sheet1!AS3 -> 83 | V8: =Sheet1!AT3 -> 95
D9: =Sheet1!AB3 -> 235 | F9: =Sheet1!AC3 -> 263
H11: Average Income | X11: Variables
X12: 1 | Z12: 2 | AB12: 3
H13: =Sheet1!AV3 -> 57618.147
X14: 20000 | Z14: 0.2 | AB14: 50000
H16: Average Value of Car
H18: =Sheet1!AY3 -> 28045.354
H21: Number of peaople with debt greater than x (1)
H23: =Sheet1!BB3 -> 398
H26: No. of People that has X% left in their mortgage (2)
H28: =Sheet1!BF3 -> 110
H31: Percentage of people having debts higher than their income (3)
H33: =Sheet1!BM3 -> 66.465863 | L33: Average Income per Sector
L34: Teaching | N34: Health | P34: Agriculture | R34: IT | T34: Construction | V34: General Work
L35: =Sheet1!BK5 -> 60813.012 | N35: =Sheet1!BK3 -> 55021.986 | P35: =Sheet1!BK7 -> 60521.135 | R35: =Sheet1!BK6 -> 57357.862 | T35: =Sheet1!BK4 -> 55980.892 | V35: =Sheet1!BK8 -> 56261.105
H36: Average age of people with a netwoth higher than their yealy income
H38: =Sheet1!BO3 -> 34.732932
D54: Average Income per Territory
D55: =TRANSPOSE({"Yukon";"British Columbia";"Northwest Territories";"Alberta";"Nunavut";"Saskatchewan";"Manitoba";"Ontario";"Quebec";"Newfoundland and Labrador";"New Brunswick";"Nova Scotia";"Prince Edward Island"}) -> Yukon | F55: British Columbia | H55: Northwest Territories | J55: Alberta | L55: Nunavut | N55: Saskatchewan | P55: Manitoba | R55: Ontario | T55: Quebec | V55: Newfoundland and Labrador | X55: New Brunswick | Z55: Nova Scotia | AB55: Prince Edward Island
D56: =Sheet1!BH3 -> 59341.919 | F56: =Sheet1!BH4 -> 60571.184 | H56: =Sheet1!BH5 -> 56748.488 | J56: =Sheet1!BH6 -> 59270.676 | L56: =Sheet1!BH7 -> 59588.545 | N56: =Sheet1!BH8 -> 58314.577 | P56: =Sheet1!BH9 -> 56639.28 | R56: =Sheet1!BH10 -> 53553.78 | T56: =Sheet1!BH11 -> 52561.25 | V56: =Sheet1!BH12 -> 55601.882 | X56: =Sheet1!BH13 -> 58167.925 | Z56: =Sheet1!BH14 -> 55032.455 | AB56: =Sheet1!BH15 -> 61583.062
